automato/__init__.py
automato/automato.py
automato/bottleneck_bootstrap/__init__.py
automato/bottleneck_bootstrap/bottleneck_bootstrap.py
automato/persistence_plotting/__init__.py
automato/persistence_plotting/cs_wong.py
automato/persistence_plotting/persistence_plotting.py
automato-0.1.1.dist-info/licenses/LICENSE
automato-0.1.1.dist-info/METADATA
automato-0.1.1.dist-info/WHEEL
automato-0.1.1.dist-info/entry_points.txt
automato-0.1.1.dist-info/top_level.txt
automato-0.1.1.dist-info/RECORD
