Metadata-Version: 2.4
Name: automato
Version: 0.1.1
Summary: Implementation of the AuToMATo clustering algorithm.
Author-email: m-a-huber <mariushuber2@gmail.com>
License-Expression: AGPL-3.0
Project-URL: Homepage, https://github.com/m-a-huber/automato
Project-URL: Issues, https://github.com/m-a-huber/automato/issues
Requires-Python: >=3.10
License-File: LICENSE
Requires-Dist: gudhi>=3.11.0
Requires-Dist: igraph>=0.11.9
Requires-Dist: joblib>=1.5.1
Requires-Dist: numpy>=2.2.6
Requires-Dist: plotly>=6.2.0
Requires-Dist: scikit-learn>=1.7.1
Dynamic: license-file
